ng3/__init__.py
ng3/graph_navigator.py
ng3/ng3_cmd.py
ng3/ng3_demo.py
ng3/version.py
nicegraph-0.0.2.dist-info/METADATA
nicegraph-0.0.2.dist-info/WHEEL
nicegraph-0.0.2.dist-info/entry_points.txt
nicegraph-0.0.2.dist-info/licenses/LICENSE
nicegraph-0.0.2.dist-info/RECORD
